README.md
setup.cfg
setup.py
examples/__init__.py
fastapi_asyncpg/__init__.py
fastapi_asyncpg/sql.py
fastapi_asyncpg.egg-info/PKG-INFO
fastapi_asyncpg.egg-info/SOURCES.txt
fastapi_asyncpg.egg-info/dependency_links.txt
fastapi_asyncpg.egg-info/requires.txt
fastapi_asyncpg.egg-info/top_level.txt