Metadata-Version: 2.1
Name: fastapi-asyncpg
Version: 1.0.1
Summary: FastAPI integration for asyncpg
Home-page: https://github.com/jordic/fastapi_asyncpg
Author: Jordi collell
Author-email: jordic@gmail.com
License: MIT
Platform: UNKNOWN
Classifier: License :: OSI Approved :: MIT License
Classifier: Programming Language :: Python
Classifier: Programming Language :: Python :: 3
Classifier: Programming Language :: Python :: 3.6
Classifier: Programming Language :: Python :: 3.7
Classifier: Programming Language :: Python :: 3.8
Classifier: Programming Language :: Python :: 3.9
Provides-Extra: dev
Provides-Extra: docs
Provides-Extra: test
Provides-Extra: publish
